fda_snitch/__init__.py
fda_snitch/fda_snitch.py
fda_snitch/assets/censor-beep-2.wav
fda_snitch-0.1.4.dist-info/METADATA
fda_snitch-0.1.4.dist-info/WHEEL
fda_snitch-0.1.4.dist-info/top_level.txt
fda_snitch-0.1.4.dist-info/RECORD
