Metadata-Version: 2.1
Name: fda-snitch
Version: 0.1.4
Summary: FDA Snitch package 
Home-page: UNKNOWN
Author: Casper Kaandorp
Author-email: casper@compunist.nl
License: UNKNOWN
Platform: UNKNOWN
Classifier: Programming Language :: Python :: 3
Classifier: Operating System :: OS Independent
Requires-Python: >=3.6
